{
    "instance-scheduler-ConfigTable-16ALRZVZ4DW72": [
        {
            "PutRequest": {
                "Item": {
                    "type": {
                        "S": "schedule"
                    },
                    "timezone": {
                        "S": "US/Pacific"
                    },
                    "name": {
                        "S": "mon-fri-all-day-pacific"
                    },
                    "description": {
                        "S": "Monday to Friday (all day) for US/Pacific"
                    },
                    "periods": {
                        "SS": [
                            "working-days"
                        ]
                    }
                }
            }
        },
        {
            "PutRequest": {
                "Item": {
                    "type": {
                        "S": "schedule"
                    },
                    "timezone": {
                        "S": "US/Arizona"
                    },
                    "name": {
                        "S": "mon-fri-all-day-arizona"
                    },
                    "description": {
                        "S": "Monday to Friday (all day) for US/Arizona"
                    },
                    "periods": {
                        "SS": [
                            "working-days"
                        ]
                    }
                }
            }
        },
        {
            "PutRequest": {
                "Item": {
                    "type": {
                        "S": "schedule"
                    },
                    "timezone": {
                        "S": "America/Mexico_City"
                    },
                    "name": {
                        "S": "mon-fri-all-day-mexico-city"
                    },
                    "description": {
                        "S": "Monday to Friday (all day) for America/Mexico_City"
                    },
                    "periods": {
                        "SS": [
                            "working-days"
                        ]
                    }
                }
            }
        },
        {
            "PutRequest": {
                "Item": {
                    "type": {
                        "S": "schedule"
                    },
                    "timezone": {
                        "S": "US/Central"
                    },
                    "name": {
                        "S": "mon-fri-all-day-central"
                    },
                    "description": {
                        "S": "Monday to Friday (all day) for US/Central"
                    },
                    "periods": {
                        "SS": [
                            "working-days"
                        ]
                    }
                }
            }
        },
        {
            "PutRequest": {
                "Item": {
                    "type": {
                        "S": "schedule"
                    },
                    "timezone": {
                        "S": "America/Bogota"
                    },
                    "name": {
                        "S": "mon-fri-all-day-bogota"
                    },
                    "description": {
                        "S": "Monday to Friday (all day) for America/Bogota"
                    },
                    "periods": {
                        "SS": [
                            "working-days"
                        ]
                    }
                }
            }
        },
        {
            "PutRequest": {
                "Item": {
                    "type": {
                        "S": "schedule"
                    },
                    "timezone": {
                        "S": "America/Caracas"
                    },
                    "name": {
                        "S": "mon-fri-all-day-caracas"
                    },
                    "description": {
                        "S": "Monday to Friday (all day) for America/Caracas"
                    },
                    "periods": {
                        "SS": [
                            "working-days"
                        ]
                    }
                }
            }
        },
        {
            "PutRequest": {
                "Item": {
                    "type": {
                        "S": "schedule"
                    },
                    "timezone": {
                        "S": "America/La_Paz"
                    },
                    "name": {
                        "S": "mon-fri-all-day-la-paz"
                    },
                    "description": {
                        "S": "Monday to Friday (all day) for America/La_Paz"
                    },
                    "periods": {
                        "SS": [
                            "working-days"
                        ]
                    }
                }
            }
        },
        {
            "PutRequest": {
                "Item": {
                    "type": {
                        "S": "schedule"
                    },
                    "timezone": {
                        "S": "America/Buenos_Aires"
                    },
                    "name": {
                        "S": "mon-fri-all-day-buenos-aires"
                    },
                    "description": {
                        "S": "Monday to Friday (all day) for America/Buenos_Aires"
                    },
                    "periods": {
                        "SS": [
                            "working-days"
                        ]
                    }
                }
            }
        },
        {
            "PutRequest": {
                "Item": {
                    "type": {
                        "S": "schedule"
                    },
                    "timezone": {
                        "S": "Atlantic/Azores"
                    },
                    "name": {
                        "S": "mon-fri-all-day-azores"
                    },
                    "description": {
                        "S": "Monday to Friday (all day) for Atlantic/Azores"
                    },
                    "periods": {
                        "SS": [
                            "working-days"
                        ]
                    }
                }
            }
        },
        {
            "PutRequest": {
                "Item": {
                    "type": {
                        "S": "schedule"
                    },
                    "timezone": {
                        "S": "Europe/London"
                    },
                    "name": {
                        "S": "mon-fri-all-day-london"
                    },
                    "description": {
                        "S": "Monday to Friday (all day) for Europe/London"
                    },
                    "periods": {
                        "SS": [
                            "working-days"
                        ]
                    }
                }
            }
        },
        {
            "PutRequest": {
                "Item": {
                    "type": {
                        "S": "schedule"
                    },
                    "timezone": {
                        "S": "Europe/Athens"
                    },
                    "name": {
                        "S": "mon-fri-all-day-athens"
                    },
                    "description": {
                        "S": "Monday to Friday (all day) for Europe/Athens"
                    },
                    "periods": {
                        "SS": [
                            "working-days"
                        ]
                    }
                }
            }
        },
        {
            "PutRequest": {
                "Item": {
                    "type": {
                        "S": "schedule"
                    },
                    "timezone": {
                        "S": "Europe/Moscow"
                    },
                    "name": {
                        "S": "mon-fri-all-day-moscow"
                    },
                    "description": {
                        "S": "Monday to Friday (all day) for Europe/Moscow"
                    },
                    "periods": {
                        "SS": [
                            "working-days"
                        ]
                    }
                }
            }
        },
        {
            "PutRequest": {
                "Item": {
                    "type": {
                        "S": "schedule"
                    },
                    "timezone": {
                        "S": "Asia/Tehran"
                    },
                    "name": {
                        "S": "mon-fri-all-day-tehran"
                    },
                    "description": {
                        "S": "Monday to Friday (all day) for Asia/Tehran"
                    },
                    "periods": {
                        "SS": [
                            "working-days"
                        ]
                    }
                }
            }
        },
        {
            "PutRequest": {
                "Item": {
                    "type": {
                        "S": "schedule"
                    },
                    "timezone": {
                        "S": "Asia/Kabul"
                    },
                    "name": {
                        "S": "mon-fri-all-day-kabul"
                    },
                    "description": {
                        "S": "Monday to Friday (all day) for Asia/Kabul"
                    },
                    "periods": {
                        "SS": [
                            "working-days"
                        ]
                    }
                }
            }
        },
        {
            "PutRequest": {
                "Item": {
                    "type": {
                        "S": "schedule"
                    },
                    "timezone": {
                        "S": "Asia/Karachi"
                    },
                    "name": {
                        "S": "mon-fri-all-day-karachi"
                    },
                    "description": {
                        "S": "Monday to Friday (all day) for Asia/Karachi"
                    },
                    "periods": {
                        "SS": [
                            "working-days"
                        ]
                    }
                }
            }
        },
        {
            "PutRequest": {
                "Item": {
                    "type": {
                        "S": "schedule"
                    },
                    "timezone": {
                        "S": "Asia/Kolkata"
                    },
                    "name": {
                        "S": "mon-fri-all-day-kolkata"
                    },
                    "description": {
                        "S": "Monday to Friday (all day) for Asia/Kolkata"
                    },
                    "periods": {
                        "SS": [
                            "working-days"
                        ]
                    }
                }
            }
        },
        {
            "PutRequest": {
                "Item": {
                    "type": {
                        "S": "schedule"
                    },
                    "timezone": {
                        "S": "Asia/Yekaterinburg"
                    },
                    "name": {
                        "S": "mon-fri-all-day-yekaterinburg"
                    },
                    "description": {
                        "S": "Monday to Friday (all day) for Asia/Yekaterinburg"
                    },
                    "periods": {
                        "SS": [
                            "working-days"
                        ]
                    }
                }
            }
        },
        {
            "PutRequest": {
                "Item": {
                    "type": {
                        "S": "schedule"
                    },
                    "timezone": {
                        "S": "Asia/Jakarta"
                    },
                    "name": {
                        "S": "mon-fri-all-day-jakarta"
                    },
                    "description": {
                        "S": "Monday to Friday (all day) for Asia/Jakarta"
                    },
                    "periods": {
                        "SS": [
                            "working-days"
                        ]
                    }
                }
            }
        },
        {
            "PutRequest": {
                "Item": {
                    "type": {
                        "S": "schedule"
                    },
                    "timezone": {
                        "S": "Asia/Manila"
                    },
                    "name": {
                        "S": "mon-fri-all-day-manila"
                    },
                    "description": {
                        "S": "Monday to Friday (all day) for Asia/Manila"
                    },
                    "periods": {
                        "SS": [
                            "working-days"
                        ]
                    }
                }
            }
        },
        {
            "PutRequest": {
                "Item": {
                    "type": {
                        "S": "schedule"
                    },
                    "timezone": {
                        "S": "Asia/Pyongyang"
                    },
                    "name": {
                        "S": "mon-fri-all-day-pyongyang"
                    },
                    "description": {
                        "S": "Monday to Friday (all day) for Asia/Pyongyang"
                    },
                    "periods": {
                        "SS": [
                            "working-days"
                        ]
                    }
                }
            }
        },
        {
            "PutRequest": {
                "Item": {
                    "type": {
                        "S": "schedule"
                    },
                    "timezone": {
                        "S": "Asia/Hong_Kong"
                    },
                    "name": {
                        "S": "mon-fri-all-day-hong-kong"
                    },
                    "description": {
                        "S": "Monday to Friday (all day) for Asia/Hong_Kong"
                    },
                    "periods": {
                        "SS": [
                            "working-days"
                        ]
                    }
                }
            }
        },
        {
            "PutRequest": {
                "Item": {
                    "type": {
                        "S": "schedule"
                    },
                    "timezone": {
                        "S": "Asia/Tokyo"
                    },
                    "name": {
                        "S": "mon-fri-all-day-tokyo"
                    },
                    "description": {
                        "S": "Monday to Friday (all day) for Asia/Tokyo"
                    },
                    "periods": {
                        "SS": [
                            "working-days"
                        ]
                    }
                }
            }
        },
        {
            "PutRequest": {
                "Item": {
                    "type": {
                        "S": "schedule"
                    },
                    "timezone": {
                        "S": "Australia/Adelaide"
                    },
                    "name": {
                        "S": "mon-fri-all-day-adelaide"
                    },
                    "description": {
                        "S": "Monday to Friday (all day) for Australia/Adelaide"
                    },
                    "periods": {
                        "SS": [
                            "working-days"
                        ]
                    }
                }
            }
        },
        {
            "PutRequest": {
                "Item": {
                    "type": {
                        "S": "schedule"
                    },
                    "timezone": {
                        "S": "Asia/Yakutsk"
                    },
                    "name": {
                        "S": "mon-fri-all-day-yakutsk"
                    },
                    "description": {
                        "S": "Monday to Friday (all day) for Asia/Yakutsk"
                    },
                    "periods": {
                        "SS": [
                            "working-days"
                        ]
                    }
                }
            }
        },
        {
            "PutRequest": {
                "Item": {
                    "type": {
                        "S": "schedule"
                    },
                    "timezone": {
                        "S": "Asia/Vladivostok"
                    },
                    "name": {
                        "S": "mon-fri-all-day-vladivostok"
                    },
                    "description": {
                        "S": "Monday to Friday (all day) for Asia/Vladivostok"
                    },
                    "periods": {
                        "SS": [
                            "working-days"
                        ]
                    }
                }
            }
        }
    ]
}
